{
  "collapse-filter": false,
  "search": "tag:#tomas",
  "showTags": false,
  "showAttachments": false,
  "hideUnresolved": false,
  "showOrphans": true,
  "collapse-color-groups": false,
  "colorGroups": [
    {
      "query": "tag:#databaze_a_web",
      "color": {
        "a": 1,
        "rgb": 14048348
      }
    },
    {
      "query": "tag:#spolecna_informatika  ",
      "color": {
        "a": 1,
        "rgb": 14069084
      }
    }
  ],
  "collapse-display": true,
  "showArrow": false,
  "textFadeMultiplier": 0,
  "nodeSizeMultiplier": 1,
  "lineSizeMultiplier": 1,
  "collapse-forces": true,
  "centerStrength": 0.518713248970312,
  "repelStrength": 10,
  "linkStrength": 1,
  "linkDistance": 250,
  "scale": 1.305950588838692,
  "close": false
}